{
  "summary": {
    "buildDuration": "28ms",
    "totalFiles": 98,
    "totalSize": "6.6 MB",
    "booksWithContent": "14/66",
    "totalChapters": 330,
    "errors": 0,
    "warnings": 0
  },
  "breakdown": {
    "files": {
      "total": 98,
      "html": 78,
      "css": 2,
      "js": 6,
      "json": 3,
      "other": 9
    },
    "sizes": {
      "html": "6.4 MB",
      "css": "16.8 KB",
      "js": "83.1 KB",
      "json": "81.6 KB",
      "other": "23.2 KB",
      "total": "6.6 MB"
    }
  },
  "content": {
    "books": {
      "total": 66,
      "withSummaries": 14,
      "withVideos": 66,
      "totalChapters": 330
    }
  },
  "issues": {
    "errors": [],
    "warnings": []
  },
  "metadata": {
    "buildStart": "2025-08-25T14:49:41.065Z",
    "buildEnd": "2025-08-25T14:49:41.093Z",
    "buildDuration": 28,
    "timestamp": "2025-08-25T14:49:41.093Z"
  }
}